ci.py
ci-0.1.1.dist-info/LICENSE
ci-0.1.1.dist-info/METADATA
ci-0.1.1.dist-info/WHEEL
ci-0.1.1.dist-info/entry_points.txt
ci-0.1.1.dist-info/top_level.txt
ci-0.1.1.dist-info/RECORD
