Metadata-Version: 2.1
Name: ci
Version: 0.1.1
Summary: Easily run common CI tasks for Python builds.
Home-page: https://github.com/rossmacarthur/python-ci
Author: Ross MacArthur
Author-email: ross@macarthur.io
License: MIT
Download-URL: https://github.com/rossmacarthur/python-ci/archive/0.1.1.tar.gz
Project-URL: Issue Tracker, https://github.com/rossmacarthur/python-ci/issues
Platform: UNKNOWN
Classifier: License :: OSI Approved :: MIT License
Classifier: Natural Language :: English
Classifier: Programming Language :: Python
Classifier: Programming Language :: Python :: 2
Classifier: Programming Language :: Python :: 2.7
Classifier: Programming Language :: Python :: 3
Classifier: Programming Language :: Python :: 3.4
Classifier: Programming Language :: Python :: 3.5
Classifier: Programming Language :: Python :: 3.6
Classifier: Programming Language :: Python :: 3.7
Classifier: Programming Language :: Python :: Implementation :: CPython
Requires-Python: >=2.7, !=3.0.*, !=3.1.*, !=3.2.*, !=3.3.*
Provides-Extra: dev.lint
Provides-Extra: dev.test
